dmarc_metrics_exporter/__init__.py
dmarc_metrics_exporter/__main__.py
dmarc_metrics_exporter/app.py
dmarc_metrics_exporter/deserialization.py
dmarc_metrics_exporter/dmarc_event.py
dmarc_metrics_exporter/dmarc_metrics.py
dmarc_metrics_exporter/expiring_set.py
dmarc_metrics_exporter/imap_client.py
dmarc_metrics_exporter/imap_parser.py
dmarc_metrics_exporter/imap_queue.py
dmarc_metrics_exporter/logging.py
dmarc_metrics_exporter/metrics_persister.py
dmarc_metrics_exporter/model/__init__.py
dmarc_metrics_exporter/model/dmarc_aggregate_report.py
dmarc_metrics_exporter/model/tests/__init__.py
dmarc_metrics_exporter/model/tests/sample_data.py
dmarc_metrics_exporter/model/tests/test_deserialization.py
dmarc_metrics_exporter/prometheus_exporter.py
dmarc_metrics_exporter/tests/__init__.py
dmarc_metrics_exporter/tests/conftest.py
dmarc_metrics_exporter/tests/sample_emails.py
dmarc_metrics_exporter/tests/test_app.py
dmarc_metrics_exporter/tests/test_deserialization.py
dmarc_metrics_exporter/tests/test_dmarc_metrics.py
dmarc_metrics_exporter/tests/test_e2e.py
dmarc_metrics_exporter/tests/test_expiring_set.py
dmarc_metrics_exporter/tests/test_imap_client.py
dmarc_metrics_exporter/tests/test_imap_parser.py
dmarc_metrics_exporter/tests/test_imap_queue.py
dmarc_metrics_exporter/tests/test_logging.py
dmarc_metrics_exporter/tests/test_metrics_persister.py
dmarc_metrics_exporter/tests/test_prometheus_exporter.py
dmarc_metrics_exporter-1.2.0.dist-info/LICENSE
dmarc_metrics_exporter-1.2.0.dist-info/METADATA
dmarc_metrics_exporter-1.2.0.dist-info/WHEEL
dmarc_metrics_exporter-1.2.0.dist-info/entry_points.txt
dmarc_metrics_exporter-1.2.0.dist-info/RECORD
