Metadata-Version: 2.1
Name: dmarc-metrics-exporter
Version: 1.2.0
Summary: Export Prometheus metrics from DMARC reports.
Home-page: https://github.com/jgosmann/dmarc-metrics-exporter/
License: MIT
Keywords: DMARC,DKIM,SPF,Prometheus
Author: Jan Gosmann
Author-email: jan@hyper-world.de
Requires-Python: >=3.9,<4.0
Classifier: Development Status :: 5 - Production/Stable
Classifier: Framework :: AsyncIO
Classifier: Intended Audience :: System Administrators
Classifier: License :: OSI Approved :: MIT License
Classifier: Programming Language :: Python :: 3
Classifier: Programming Language :: Python :: 3.9
Classifier: Programming Language :: Python :: 3.10
Classifier: Programming Language :: Python :: 3.11
Classifier: Programming Language :: Python :: 3.12
Classifier: Programming Language :: Python :: 3.13
Classifier: Programming Language :: Python :: 3 :: Only
Classifier: Topic :: Communications :: Email
Classifier: Topic :: System :: Monitoring
Requires-Dist: bite-parser (>=0.2.4,<0.3.0)
Requires-Dist: dataclasses-serialization (>=1.3.1,<2.0.0)
Requires-Dist: prometheus_client (>=0.21.0,<0.22.0)
Requires-Dist: structlog (>=24.1.0)
Requires-Dist: uvicorn[standard] (>=0.32.0,<0.33.0)
Requires-Dist: xsdata (>=23.7)
Project-URL: Repository, https://github.com/jgosmann/dmarc-metrics-exporter/
